bol_SDK/__init__.py
bol_SDK/__main__.py
bol_SDK/bol_SDK.py
bol_SDK/constants.py
bol_sdk-0.1.7.dist-info/WHEEL
bol_sdk-0.1.7.dist-info/METADATA
bol_sdk-0.1.7.dist-info/RECORD
